{
  "id": "planform-freeze",
  "type": "deliverable",
  "name": "Planform freeze",
  "description": "Concept review deliverable — frozen wing and empennage planform geometry.",
  "date": "2027-07-11",
  "predecessors": [
    "evaluate-f100-handling-qualities-concept",
    "evaluate-f100-performance"
  ],
  "status": "planned",
  "tags": [
    "aircraft-design",
    "deliverable",
    "concept-review",
    "planform",
    "configuration"
  ],
  "row": 9,
  "discipline": "overall-aircraft-design",
  "subrow": 1
}
